LICENSE.md
MANIFEST.in
README.md
__init__.py
setup.cfg
setup.py
collective/__init__.py
collective/__init__.pyc
collective.newrelic.egg-info/PKG-INFO
collective.newrelic.egg-info/SOURCES.txt
collective.newrelic.egg-info/dependency_links.txt
collective.newrelic.egg-info/entry_points.txt
collective.newrelic.egg-info/namespace_packages.txt
collective.newrelic.egg-info/not-zip-safe
collective.newrelic.egg-info/requires.txt
collective.newrelic.egg-info/top_level.txt
collective/newrelic/__init__.py
collective/newrelic/__init__.pyc
collective/newrelic/configure.zcml
collective/newrelic/hooks.py
collective/newrelic/hooks.pyc
collective/newrelic/utils.py
collective/newrelic/utils.pyc
collective/newrelic/patches/__init__.py
collective/newrelic/patches/__init__.pyc
collective/newrelic/patches/catalog_tool.py
collective/newrelic/patches/catalog_tool.pyc
collective/newrelic/patches/cron4plone.py
collective/newrelic/patches/cron4plone.pyc
collective/newrelic/patches/newrelic_transaction.py
collective/newrelic/patches/newrelic_transaction.pyc
collective/newrelic/patches/talinterpreter.py
collective/newrelic/patches/talinterpreter.pyc
collective/newrelic/patches/transformchains.py
collective/newrelic/patches/transformchains.pyc
collective/newrelic/patches/zope_event.py
collective/newrelic/patches/zope_event.pyc
collective/newrelic/patches/zpublisher_mapply.py
collective/newrelic/patches/zpublisher_mapply.pyc
collective/newrelic/patches/zserverpublisher.py
collective/newrelic/patches/zserverpublisher.pyc
collective/newrelic/transforms/__init__.py
collective/newrelic/transforms/__init__.pyc
collective/newrelic/transforms/configure.zcml
collective/newrelic/transforms/outputfilter.py
collective/newrelic/transforms/outputfilter.pyc
docs/HISTORY.txt
docs/TODO.txt