Metadata-Version: 1.0
Name: collective.newrelic
Version: 1.0.9
Summary: Zope/Plone Newrelic instrumentation
Home-page: https://github.com/collective/collective.newrelic
Author: Douwe van der Meij, Peter Uittenbroek
Author-email: support@gw20e.com
License: GPL
Platform: UNKNOWN
Classifier: Framework :: Plone
Classifier: Programming Language :: Python
